main.py
getting_started_harshit_cognitree-0.1.0.dist-info/METADATA
getting_started_harshit_cognitree-0.1.0.dist-info/WHEEL
getting_started_harshit_cognitree-0.1.0.dist-info/top_level.txt
getting_started_harshit_cognitree-0.1.0.dist-info/RECORD
