Metadata-Version: 2.1
Name: getting-started-harshit-cognitree
Version: 0.1.0
Summary: Simple calculator application
